LICENSE
MANIFEST.in
README.rst
setup.py
sentry_graphite/__init__.py
sentry_graphite.egg-info/PKG-INFO
sentry_graphite.egg-info/SOURCES.txt
sentry_graphite.egg-info/dependency_links.txt
sentry_graphite.egg-info/not-zip-safe
sentry_graphite.egg-info/requires.txt
sentry_graphite.egg-info/top_level.txt