Metadata-Version: 1.0
Name: sentry-graphite
Version: 0.1.0
Summary: A Sentry extension that counts events in Graphite
Home-page: http://github.com/disqus/sentry-graphite
Author: DISQUS
Author-email: opensource@disqus.com
License: Apache License 2.0
Keywords: sentry graphite
Platform: UNKNOWN
Classifier: Framework :: Django
Classifier: Intended Audience :: Developers
Classifier: Intended Audience :: System Administrators
Classifier: Operating System :: OS Independent
Classifier: Topic :: Software Development
